.DS_Store
microtubule_pkg/__init__.py
microtubule_pkg/stats.py
microtubule_meganwang08-0.0.3.dist-info/LICENSE.md
microtubule_meganwang08-0.0.3.dist-info/METADATA
microtubule_meganwang08-0.0.3.dist-info/WHEEL
microtubule_meganwang08-0.0.3.dist-info/top_level.txt
microtubule_meganwang08-0.0.3.dist-info/RECORD
