Metadata-Version: 2.1
Name: microtubule-meganwang08
Version: 0.0.3
Summary: microtubule catastrophe Bebi103a package
Home-page: https://github.com/meganwang08/micotubule
Author: Megan Wang
Author-email: yinghan@caltech.edu
License: UNKNOWN
Platform: UNKNOWN
Classifier: Programming Language :: Python :: 3
Classifier: License :: OSI Approved :: MIT License
Classifier: Operating System :: OS Independent
Requires-Python: >=3.6
Requires-Dist: numpy
Requires-Dist: pandas
Requires-Dist: bokeh (>=1.4.0)
